agentbenchkit/__about__.py
agentbenchkit/__init__.py
agentbenchkit/core/__init__.py
agentbenchkit/core/executor.py
agentbenchkit/core/prompt.py
agentbenchkit/core/utils.py
agentbenchkit/core/workflow.py
agentbenchkit/evaluator/IOU_match.py
agentbenchkit/evaluator/__init__.py
agentbenchkit/evaluator/anls.py
agentbenchkit/evaluator/exact_match.py
agentbenchkit/evaluator/exact_match_2l.py
agentbenchkit/evaluator/hallucination_score.py
agentbenchkit/evaluator/hallusionbench_eval.py
agentbenchkit/evaluator/in_mask.py
agentbenchkit/evaluator/llm_compare_config.yaml
agentbenchkit/evaluator/llm_compare_eval.py
agentbenchkit/evaluator/mme_eval.py
agentbenchkit/evaluator/nlg_score.py
agentbenchkit/evaluator/ocrbench_eval.py
agentbenchkit/loader/RefSpatialBench_loader.py
agentbenchkit/loader/RoboSpatialHome_loader.py
agentbenchkit/loader/__init__.py
agentbenchkit/loader/ai2d_loader.py
agentbenchkit/loader/base.py
agentbenchkit/loader/blink_loader.py
agentbenchkit/loader/chartqa_loader.py
agentbenchkit/loader/coco_caption_2017_loader.py
agentbenchkit/loader/count_loader.py
agentbenchkit/loader/cv_bench_loader.py
agentbenchkit/loader/default_evaluator.json
agentbenchkit/loader/docvqa_loader.py
agentbenchkit/loader/embspatial_bench_loader.py
agentbenchkit/loader/erqa_loader.py
agentbenchkit/loader/hallusionbench_loader.py
agentbenchkit/loader/math500_loader.py
agentbenchkit/loader/mathverse_testmini.py
agentbenchkit/loader/mathvision_loader.py
agentbenchkit/loader/mathvista_loader.py
agentbenchkit/loader/mmbench_cn_loader.py
agentbenchkit/loader/mmbench_en_loader.py
agentbenchkit/loader/mme_loader.py
agentbenchkit/loader/mmstar_loader.py
agentbenchkit/loader/mmt_bench_val_loader.py
agentbenchkit/loader/muir_loader.py
agentbenchkit/loader/ocrbench_loader.py
agentbenchkit/loader/pope_loader.py
agentbenchkit/loader/realworld_qa_loader.py
agentbenchkit/loader/scienceqa_test_loader.py
agentbenchkit/loader/scienceqa_val_loader.py
agentbenchkit/loader/seedbench_v2_pluss_loader.py
agentbenchkit-0.0.1.dist-info/METADATA
agentbenchkit-0.0.1.dist-info/WHEEL
agentbenchkit-0.0.1.dist-info/licenses/LICENSE.txt
agentbenchkit-0.0.1.dist-info/RECORD
