Metadata-Version: 2.4
Name: agentbenchkit
Version: 0.0.1
Project-URL: Documentation, https://github.com/Shawnshen001/agentbenchkit#readme
Project-URL: Issues, https://github.com/Shawnshen001/agentbenchkit/issues
Project-URL: Source, https://github.com/Shawnshen001/agentbenchkit
Author-email: Shawnshen001 <1411355069@qq.com>
License-Expression: MIT
License-File: LICENSE.txt
Classifier: Development Status :: 4 - Beta
Classifier: Programming Language :: Python :: 3.12
Classifier: Programming Language :: Python :: Implementation :: CPython
Requires-Python: >=3.12
Requires-Dist: datasets>=4.4.1
Requires-Dist: langchain-core>=1.2.2
Requires-Dist: langchain-openai>=1.1.0
Requires-Dist: langfuse>=3.10.5
Requires-Dist: levenshtein>=0.27.3
Requires-Dist: numpy>=2.2.0
Requires-Dist: omegaconf>=2.3.0
Requires-Dist: pillow>=12.0.0
Requires-Dist: pycocoevalcap>=1.2
Requires-Dist: ray>=2.52.1
Requires-Dist: requests>=2.32.5
Requires-Dist: scikit-learn>=1.8.0
Requires-Dist: tqdm>=4.67.1
